commonutil_convert/__init__.py
commonutil_convert/container.py
commonutil_convert/primitive.py
commonutil_convert/py.typed
commonutil_convert/time_composite.py
commonutil_convert/uuid_composite.py
commonutil_convert-3.0.7.dist-info/METADATA
commonutil_convert-3.0.7.dist-info/WHEEL
commonutil_convert-3.0.7.dist-info/top_level.txt
commonutil_convert-3.0.7.dist-info/RECORD
