Metadata-Version: 2.1
Name: commonutil-convert
Version: 3.0.7
Summary: Data instance convert routines
Classifier: Development Status :: 5 - Production/Stable
Classifier: Intended Audience :: Developers
Classifier: License :: OSI Approved :: MIT License
Classifier: Operating System :: POSIX
Requires-Python: >=3.7
